opp_frontend
