Metadata-Version: 2.1
Name: openpeerpower-frontend
Version: 20210523.2
Summary: The Open Peer Power frontend
Home-page: https://github.com/openpeerpower/openpeerpower-polymer
Author: The Open Peer Power Authors
Author-email: hello@openpeerpower.io
License: Apache-2.0
Platform: UNKNOWN
License-File: LICENSE.md
